LICENSE
README.md
setup.py
help50/__init__.py
help50/__main__.py
help50/internal.py
help50.egg-info/PKG-INFO
help50.egg-info/SOURCES.txt
help50.egg-info/dependency_links.txt
help50.egg-info/entry_points.txt
help50.egg-info/requires.txt
help50.egg-info/top_level.txt